{
  "name": "contact",
  "plural": "contacts",
  "base": "PersistedModel",
  "idInjection": true,
  "options": {
    "validateUpsert": true
  },
  "properties": {
    "relationship": {
      "type": "string"
    },
    "name": {
      "type": [
        "string"
      ]
    },
    "telecom": {
      "type": [
        "string"
      ]
    },
    "address": {
      "type": [
        "string"
      ]
    },
    "gender": {
      "type": "number",
      "default": 0
    },
    "organization": {
      "type": "number"
    },
    "period": {
      "type": "any"
    }
  },
  "validations": [],
  "relations": {
    "patientContacts": {
      "type": "hasOne",
      "model": "patient",
      "foreignKey": "patientId"
    }
  },
  "acls": [],
  "methods": {}
}
